illusioncolor/__init__.py
illusioncolor/main.py
illusioncolor-0.1.dist-info/METADATA
illusioncolor-0.1.dist-info/WHEEL
illusioncolor-0.1.dist-info/top_level.txt
illusioncolor-0.1.dist-info/RECORD
