Metadata-Version: 2.1
Name: illusioncolor
Version: 0.1
Summary: This package allow you to import 255+ color to change the color of output in terminal
Author: KDO (Team Illusion)
Classifier: Development Status :: 1 - Planning
Classifier: Intended Audience :: Developers
Classifier: Programming Language :: Python :: 3
Classifier: Operating System :: Unix
Classifier: Operating System :: MacOS :: MacOS X
Classifier: Operating System :: Microsoft :: Windows
Classifier: Operating System :: POSIX :: Linux
Classifier: Operating System :: Android
